muscle/__init__.py
muscle-0.0.4.dist-info/LICENSE
muscle-0.0.4.dist-info/METADATA
muscle-0.0.4.dist-info/WHEEL
muscle-0.0.4.dist-info/top_level.txt
muscle-0.0.4.dist-info/RECORD
