Metadata-Version: 2.1
Name: muscle
Version: 0.0.4
Summary: Strength Training Program Generator
Home-page: https://github.com/rlofc/muscle
Author: ithai Levi
Author-email: randomlinesofcode@gmail.com
License: UNKNOWN
Platform: UNKNOWN
Classifier: Programming Language :: Python :: 3
Classifier: License :: OSI Approved :: MIT License
Classifier: Operating System :: OS Independent
Requires-Python: >=3.6
